bhr/__init__.py
bhr/borehole.py
bhr/coaxial_borehole.py
bhr/double_u_borehole.py
bhr/enums.py
bhr/fluid.py
bhr/pipe.py
bhr/single_u_borehole.py
bhr/tests/test_borehole.py
bhr/tests/test_coaxial_borehole.py
bhr/tests/test_double_u_borehole.py
bhr/tests/test_fluid.py
bhr/tests/test_pipe.py
bhr/tests/test_single_u_borehole.py
bhr/tests/test_u_tube.py
bhr/u_tube.py
bhr/utilities.py
bhresist-0.1.dist-info/LICENSE
bhresist-0.1.dist-info/METADATA
bhresist-0.1.dist-info/WHEEL
bhresist-0.1.dist-info/RECORD
