Metadata-Version: 2.3
Name: BHResist
Version: 0.1
Summary: Functionality to compute the thermal resistance of borehole heat exchangers
License: BSD-3-Clause
Author: Matt Mitchell
Author-email: mitchute@gmail.com
Requires-Python: >=3.9,<3.14
Classifier: License :: OSI Approved :: BSD License
Classifier: Programming Language :: Python :: 3
Classifier: Programming Language :: Python :: 3.9
Classifier: Programming Language :: Python :: 3.10
Classifier: Programming Language :: Python :: 3.11
Classifier: Programming Language :: Python :: 3.12
Classifier: Programming Language :: Python :: 3.13
Requires-Dist: SecondaryCoolantProps (>=1.3,<2.0)
Project-URL: Repository, https://github.com/NREL/BHResist
